tcclient/__init__.py
tcclient-0.0.4.dist-info/METADATA
tcclient-0.0.4.dist-info/WHEEL
tcclient-0.0.4.dist-info/top_level.txt
tcclient-0.0.4.dist-info/RECORD
