Metadata-Version: 2.1
Name: tcclient
Version: 0.0.4
Summary: The cross-platform tool to with the TC server remotely.
Home-page: https://github.com/c-pher/tcclient
Author: Andrey Komissarov
Author-email: a.komisssarov@gmail.com
License: GNU General Public License v3.0
Platform: UNKNOWN
Classifier: Programming Language :: Python :: 3
Classifier: License :: OSI Approved :: GNU General Public License v3 (GPLv3)
Classifier: Operating System :: OS Independent
Requires-Python: >=3.6
Requires-Dist: requests (>=2.25.1)
Requires-Dist: plogger (>=1.0.6)
